<?xml version="1.0" encoding="UTF-8"?>
<beans xmlns="http://www.springframework.org/schema/beans"
	xmlns:xsi="http://www.w3.org/2001/XMLSchema-instance"
	xmlns:mvc="http://www.springframework.org/schema/mvc"
	xmlns:context="http://www.springframework.org/schema/context"
	xmlns:task="http://www.springframework.org/schema/task"
	xsi:schemaLocation="http://www.springframework.org/schema/mvc http://www.springframework.org/schema/mvc/spring-mvc-3.0.xsd
		http://www.springframework.org/schema/aop http://www.springframework.org/schema/aop/spring-aop.xsd
		http://www.springframework.org/schema/beans http://www.springframework.org/schema/beans/spring-beans-3.0.xsd
		http://www.springframework.org/schema/context http://www.springframework.org/schema/context/spring-context-3.0.xsd
		http://www.springframework.org/schema/task http://www.springframework.org/schema/task/spring-task.xsd">

<mvc:annotation-driven />

<mvc:resources mapping="/resources/**" location="/resources/" />

<bean class="org.springframework.web.servlet.view.InternalResourceViewResolver">
	<property name="prefix" value="/WEB-INF/views/" />
	<property name="suffix" value=".jsp" /> 
</bean>

<mvc:interceptors>
	<mvc:interceptor>
		<mvc:mapping path="/member/myMusic"/>
		<bean class="kr.kina.interceptor.LoginInterceptor"></bean>
	</mvc:interceptor>
</mvc:interceptors>

<bean id="jacksonMessageConverter" class="org.springframework.http.converter.json.MappingJackson2HttpMessageConverter" />

<!-- threadPool 
<bean class="org.springframework.scheduling.concurrent.ConcurrentTaskExecutor" id="taskExecutor" >
	<property name="corePoolSize" value="10" />
	<property name="maxPoolSize" value="25" />
	<property name="queueCapacity" value="30" />
</bean>

<bean id="TaskExecutor" class="TaskExecutor">
	<constructor-arg ref="TaskExecutor" />
</bean> -->

<context:component-scan base-package="kr.kina.controller, kr.kina.interceptor" />
</beans>